morpheus_mcpi/__init__.py
morpheus_mcpi/__main__.py
morpheus_mcpi/spectator_mode.py
morpheus_mcpi-2.2.dist-info/LICENSE
morpheus_mcpi-2.2.dist-info/METADATA
morpheus_mcpi-2.2.dist-info/WHEEL
morpheus_mcpi-2.2.dist-info/entry_points.txt
morpheus_mcpi-2.2.dist-info/top_level.txt
morpheus_mcpi-2.2.dist-info/RECORD
