Metadata-Version: 2.1
Name: morpheus-mcpi
Version: 2.2
Summary: A set of tools to improve the user's experience in Minecraft: Pi Edition.
Home-page: https://github.com/bigjango13/Morpheus-2
Author: bigjango13
License: MIT
Platform: UNKNOWN
Classifier: Development Status :: 5 - Production/Stable
Classifier: Programming Language :: Python :: 3
Requires-Dist: keyboard
Requires-Dist: mcpi
Requires-Dist: pysimplegui
